[
	{
		"NAME": "Barcena, Blincent Addam",
		"POSITION": "MANAGER",
		"TEAM": [
			{ "NAME": "Bongalbal, Ronnel", "POSITION": "DEPUTY MANAGER" },
			{ "NAME": "Calma, Voughn Emil", "POSITION": "SENIOR GIS SPECIALIST" },
			{ "NAME": "De Jesus, Edgar Chevy", "POSITION": "SENIOR GIS SPECIALIST" },
			{ "NAME": "Encarnado, Gerik Ivan", "POSITION": "SENIOR GIS SPECIALIST" },
			{ "NAME": "See, Eliza Kathleen", "POSITION": "SENIOR GIS SPECIALIST" },
			{ "NAME": "Wenceslao, Roesel", "POSITION": "SENIOR GIS SPECIALIST" },
			{ "NAME": "Zapanta, Andrew", "POSITION": "SENIOR GIS OPERATOR" },
			{ "NAME": "Sana, Abegail", "POSITION": "LEAD SENIOR LAND TECHNICAL SPECIALIST" },
			{ "NAME": "Cutamora, Marc Justin", "POSITION": "LEAD SENIOR LAND TECHNICAL SPECIALIST" }
		]
	},
	{
		"NAME": "Bongalbal, Ronnel",
		"POSITION": "DEPUTY MANAGER",
		"TEAM": [
			{ "NAME": "Lafuente, Rj", "POSITION": "JUNIOR GIS SPECIALIST" },
			{ "NAME": "Postrado, Jay", "POSITION": "JUNIOR GIS SPECIALIST" }
		]
	},
	{
		"NAME": "Calma, Voughn Emil",
		"POSITION": "SENIOR GIS SPECIALIST",
		"TEAM": [
			{ "NAME": "Cinco, Creesialyn Anne", "POSITION": "JUNIOR GIS SPECIALIST" },
			{ "NAME": "De Guzman, Kyle Ashley Rae", "POSITION": "JUNIOR GIS SPECIALIST" },
			{ "NAME": "Lariba, Keith Jones Paul", "POSITION": "JUNIOR GIS SPECIALIST" }
		]
	},
	{
		"NAME": "De Jesus, Edgar Chevy",
		"POSITION": "SENIOR GIS SPECIALIST",
		"TEAM": [
			{ "NAME": "Cobsilen, Clifford Jr.", "POSITION": "JUNIOR GIS SPECIALIST" },
			{ "NAME": "Gerodias, Alrey John", "POSITION": "JUNIOR GIS SPECIALIST" },
			{ "NAME": "Kawi, Philip", "POSITION": "JUNIOR GIS SPECIALIST" }
		]
	},
	{
		"NAME": "Encarnado, Gerik Ivan",
		"POSITION": "SENIOR GIS SPECIALIST",
		"TEAM": [
			{ "NAME": "Cuevas, Erick Paul", "POSITION": "JUNIOR GIS SPECIALIST" },
			{ "NAME": "Etable, Joseph", "POSITION": "JUNIOR GIS SPECIALIST" },
			{ "NAME": "Nicolas, Jonalyn", "POSITION": "JUNIOR GIS SPECIALIST" }
		]
	},
	{
		"NAME": "See, Eliza Kathleen",
		"POSITION": "SENIOR GIS SPECIALIST",
		"TEAM": [
			{ "NAME": "Curaming, Vincenzo", "POSITION": "JUNIOR GIS SPECIALIST" },
			{ "NAME": "Esteves, Carl Emmanuel", "POSITION": "JUNIOR GIS SPECIALIST" },
			{ "NAME": "Viernes, Joseph", "POSITION": "JUNIOR GIS SPECIALIST" }
		]
	},
	{
		"NAME": "Wenceslao, Roesel",
		"POSITION": "SENIOR GIS SPECIALIST",
		"TEAM": [
			{ "NAME": "Laserna, Kernell", "POSITION": "JUNIOR GIS SPECIALIST" },
			{ "NAME": "Mendoza, Carlo", "POSITION": "JUNIOR GIS SPECIALIST" },
			{ "NAME": "Ordoño, Abigail Jafet", "POSITION": "JUNIOR GIS SPECIALIST" }
		]
	},
	{
		"NAME": "Zapanta, Andrew",
		"POSITION": "SENIOR GIS OPERATOR",
		"TEAM": [
			{ "NAME": "Cruz, Vjan Michael", "POSITION": "JUNIOR GIS OPERATOR" },
			{ "NAME": "Concepcion, Jamaica", "POSITION": "JUNIOR GIS OPERATOR" },
			{ "NAME": "Llegue, Michelle", "POSITION": "JUNIOR GIS OPERATOR" },
			{ "NAME": "Mendoza, Anthony", "POSITION": "JUNIOR GIS OPERATOR" },
			{ "NAME": "Salcedo, Francis", "POSITION": "JUNIOR GIS OPERATOR" }
		]
	},
	{
		"NAME": "Sana, Abegail",
		"POSITION": "LEAD SENIOR LAND TECHNICAL SPECIALIST",
		"TEAM": [
			{ "NAME": "Cruz, Jan Michael Vincent", "POSITION": "SENIOR LAND TECHNICAL SPECIALIST" },
			{ "NAME": "Dancel, Angelic", "POSITION": "SENIOR LAND TECHNICAL SPECIALIST" },
			{ "NAME": "Castilla, Regine", "POSITION": "JUNIOR LAND TECHNICAL SPECIALIST" },
			{ "NAME": "Reboroso, Sunrise", "POSITION": "JUNIOR LAND TECHNICAL SPECIALIST" },
			{ "NAME": "Rollo, Mark Gil", "POSITION": "JUNIOR LAND TECHNICAL SPECIALIST" },
			{ "NAME": "Tumbaga, Nicole", "POSITION": "JUNIOR LAND TECHNICAL SPECIALIST" }
		]
	},
	{
		"NAME": "Cutamora, Marc Justin",
		"POSITION": "LEAD SENIOR LAND TECHNICAL SPECIALIST",
		"TEAM": [
			{ "NAME": "Bernabe, Christopher", "POSITION": "SENIOR LAND TECHNICAL SPECIALIST" },
			{ "NAME": "Lorenzo, Lindley", "POSITION": "SENIOR LAND TECHNICAL SPECIALIST" },
			{ "NAME": "Dacayanan, Jessa Mae", "POSITION": "JUNIOR LAND TECHNICAL SPECIALIST" },
			{ "NAME": "Datul, Pel-jay", "POSITION": "JUNIOR LAND TECHNICAL SPECIALIST" },
			{ "NAME": "Felipe, Roberto Jr.", "POSITION": "JUNIOR LAND TECHNICAL SPECIALIST" },
			{ "NAME": "Pacada, Roniel", "POSITION": "JUNIOR LAND TECHNICAL SPECIALIST" }
		]
	}
]
